awskit/__init__.py
awskit/interfaces/__init__.py
awskit/interfaces/dynamodb.py
awskit/interfaces/s3.py
awskit/interfaces/sg.py
awskit/interfaces/sqs.py
awskit/interfaces/subnet.py
awskit/interfaces/vpc.py
awskit/lib/auth.py
dslpy-0.0.0.dist-info/METADATA
dslpy-0.0.0.dist-info/WHEEL
dslpy-0.0.0.dist-info/top_level.txt
dslpy-0.0.0.dist-info/RECORD
